ham_func/__init__.py
ham_func/ham_func.py
ham_func-0.1.0.dist-info/METADATA
ham_func-0.1.0.dist-info/WHEEL
ham_func-0.1.0.dist-info/entry_points.txt
ham_func-0.1.0.dist-info/top_level.txt
ham_func-0.1.0.dist-info/RECORD
