Metadata-Version: 2.1
Name: ham_func
Version: 0.1.0
Summary: Default template for PDM package
Author-email: sunwoo <summerham22@gmail.com>
License: MIT
Requires-Python: >=3.9
